Metadata-Version: 2.1
Name: W-RNN
Version: 0.0.0
Summary: siyus RNN functions
Author: Siyu Wang
Author-email: wangxsiyu@gmail.com
License: UNKNOWN
Platform: UNKNOWN
